sntz/__init__.py
sntz-1.0.dist-info/METADATA
sntz-1.0.dist-info/WHEEL
sntz-1.0.dist-info/top_level.txt
sntz-1.0.dist-info/RECORD
