Metadata-Version: 2.4
Name: sntz
Version: 1.0
Summary: Library made to sanitize inputs.
Author-email: SaNiTiZe <accf1836@gmail.com>
License: MIT
Keywords: security,sanitize,input,validation
Classifier: Programming Language :: Python :: 3
Classifier: Operating System :: OS Independent
Classifier: License :: OSI Approved :: MIT License
Requires-Python: >=3.6
Requires-Dist: requests>=2.0
